matterwave/__init__.py
matterwave/constants.py
matterwave/plotting.py
matterwave/py.typed
matterwave/_src/__init__.py
matterwave/_src/constants.py
matterwave/_src/fftarray_plotting.py
matterwave/_src/split_step.py
matterwave/_src/wf_tools.py
matterwave-0.5.2.dist-info/METADATA
matterwave-0.5.2.dist-info/WHEEL
matterwave-0.5.2.dist-info/licenses/LICENSE
matterwave-0.5.2.dist-info/RECORD
