Metadata-Version: 2.4
Name: matterwave
Version: 0.5.2
Summary: A library for matter wave propagation built on top of fftarray.
Project-URL: Homepage, https://github.com/QSTheory/matterwave
Project-URL: Documentation, https://qstheory.github.io/matterwave/main
Project-URL: Repository, https://github.com/QSTheory/matterwave
Project-URL: Issues, https://github.com/QSTheory/matterwave/issues
Project-URL: Changelog, https://qstheory.github.io/matterwave/main/changelog.html
Author: Stefan Seckmeyer, Gabriel Müller, Christian Struckmann
License-File: LICENSE
Classifier: Intended Audience :: Developers
Classifier: Intended Audience :: Science/Research
Classifier: License :: OSI Approved :: Apache Software License
Classifier: Operating System :: OS Independent
Classifier: Programming Language :: Python
Classifier: Programming Language :: Python :: 3
Classifier: Programming Language :: Python :: 3.11
Classifier: Programming Language :: Python :: 3.12
Classifier: Programming Language :: Python :: 3.13
Classifier: Topic :: Scientific/Engineering
Classifier: Typing :: Typed
Requires-Python: >=3.11
Requires-Dist: fftarray>=0.5
Requires-Dist: numpy>=2.0
Requires-Dist: scipy
